README.md
setup.py
transmitter/__init__.py
transmitter/constants.py
transmitter/main.py
transmitter.egg-info/PKG-INFO
transmitter.egg-info/SOURCES.txt
transmitter.egg-info/dependency_links.txt
transmitter.egg-info/entry_points.txt
transmitter.egg-info/requires.txt
transmitter.egg-info/top_level.txt
transmitter/pricefeed/__init__.py
transmitter/pricefeed/markets.py
transmitter/pricefeed/adapters/__init__.py
transmitter/pricefeed/adapters/base.py
transmitter/pricefeed/adapters/binance.py
transmitter/pricefeed/adapters/bittrex.py
transmitter/pricefeed/adapters/huobi.py
transmitter/pricefeed/adapters/ionomy.py
transmitter/pricefeed/adapters/mxc.py
transmitter/pricefeed/adapters/probit.py