Metadata-Version: 1.0
Name: transmitter
Version: 0.2.11
Summary: HIVE Witness updates made easy.
Home-page: http://github.com/emre/transmitter
Author: emre yilmaz
Author-email: mail@emreyilmaz.me
License: MIT
Platform: UNKNOWN
